MANIFEST.in
README.rst
setup.py
examples/matplotlib-setup.cfg
examples/numpy-conda.ini
examples/numpy.ini
testrig/__init__.py
testrig/__main__.py
testrig/_version.py
testrig/cli.py
testrig/fixture.py
testrig/lockfile.py
testrig/parser.py
testrig.egg-info/PKG-INFO
testrig.egg-info/SOURCES.txt
testrig.egg-info/dependency_links.txt
testrig.egg-info/entry_points.txt
testrig.egg-info/not-zip-safe
testrig.egg-info/requires.txt
testrig.egg-info/top_level.txt
testrig/tests/test_parsers.py