Metadata-Version: 1.1
Name: testrig
Version: 0.2
Summary: testrig: running tests for dependent packages
Home-page: http://github.com/pv/testrig
Author: Pauli Virtanen
Author-email: pav@iki.fi
License: BSD
Platform: UNKNOWN
Classifier: Environment :: Console
Classifier: Intended Audience :: Developers
Classifier: License :: OSI Approved :: BSD License
Classifier: Programming Language :: Python :: 2
Classifier: Programming Language :: Python :: 3
Classifier: Topic :: Software Development :: Testing
